RsCmwWcdmaSig/RsCmwWcdmaSig.py
RsCmwWcdmaSig/__init__.py
RsCmwWcdmaSig/enums.py
RsCmwWcdmaSig/repcap.py
RsCmwWcdmaSig/CustomFiles/__init__.py
RsCmwWcdmaSig/CustomFiles/events.py
RsCmwWcdmaSig/CustomFiles/reliability.py
RsCmwWcdmaSig/CustomFiles/utilities.py
RsCmwWcdmaSig/Implementations/Ber.py
RsCmwWcdmaSig/Implementations/Call.py
RsCmwWcdmaSig/Implementations/Clean.py
RsCmwWcdmaSig/Implementations/Configure.py
RsCmwWcdmaSig/Implementations/Cswitched.py
RsCmwWcdmaSig/Implementations/Eagch.py
RsCmwWcdmaSig/Implementations/Ehich.py
RsCmwWcdmaSig/Implementations/Ergch.py
RsCmwWcdmaSig/Implementations/Hack.py
RsCmwWcdmaSig/Implementations/Hcqi.py
RsCmwWcdmaSig/Implementations/Prepare.py
RsCmwWcdmaSig/Implementations/Pswitched.py
RsCmwWcdmaSig/Implementations/Route.py
RsCmwWcdmaSig/Implementations/Rsignaling.py
RsCmwWcdmaSig/Implementations/Sense.py
RsCmwWcdmaSig/Implementations/Source.py
RsCmwWcdmaSig/Implementations/Throughput.py
RsCmwWcdmaSig/Implementations/UeReport.py
RsCmwWcdmaSig/Implementations/UplinkLogging.py
RsCmwWcdmaSig/Implementations/__init__.py
RsCmwWcdmaSig/Implementations/Ber_/State.py
RsCmwWcdmaSig/Implementations/Ber_/__init__.py
RsCmwWcdmaSig/Implementations/Ber_/State_/All.py
RsCmwWcdmaSig/Implementations/Ber_/State_/__init__.py
RsCmwWcdmaSig/Implementations/Call_/Cswitched.py
RsCmwWcdmaSig/Implementations/Call_/Pswitched.py
RsCmwWcdmaSig/Implementations/Call_/Rsignaling.py
RsCmwWcdmaSig/Implementations/Call_/__init__.py
RsCmwWcdmaSig/Implementations/Clean_/Connection.py
RsCmwWcdmaSig/Implementations/Clean_/Elogging.py
RsCmwWcdmaSig/Implementations/Clean_/Sms.py
RsCmwWcdmaSig/Implementations/Clean_/__init__.py
RsCmwWcdmaSig/Implementations/Clean_/Connection_/Cswitched.py
RsCmwWcdmaSig/Implementations/Clean_/Connection_/__init__.py
RsCmwWcdmaSig/Implementations/Clean_/Connection_/Cswitched_/Attempt.py
RsCmwWcdmaSig/Implementations/Clean_/Connection_/Cswitched_/Reject.py
RsCmwWcdmaSig/Implementations/Clean_/Connection_/Cswitched_/__init__.py
RsCmwWcdmaSig-3.8.10.25.dist-info/METADATA
RsCmwWcdmaSig-3.8.10.25.dist-info/WHEEL
RsCmwWcdmaSig-3.8.10.25.dist-info/top_level.txt
RsCmwWcdmaSig-3.8.10.25.dist-info/RECORD
